shore/__init__.py
shore/__main__.py
shore/mapper.py
shore/model.py
shore/static.py
shore/core/__init__.py
shore/core/plugins.py
shore/plugins/__init__.py
shore/plugins/_util.py
shore/plugins/core.py
shore/plugins/install_script.py
shore/plugins/pypi.py
shore/plugins/requirements_file.py
shore/plugins/setuptools.py
shore/templates/install_script/install
shore/templates/monorepo/.gitignore
shore/templates/monorepo/README.md
shore/templates/monorepo/monorepo.yaml
shore/templates/package/.gitignore
shore/templates/package/README.md
shore/templates/package/package.yaml
shore/templates/package/src/test/{{name}}/__init__.py
shore/templates/package/src/test/{{name}}/test_some.py
shore/templates/package/src/{{name}}/__init__.py
shore/tools/__init__.py
shore/tools/conda_forge.py
shore/util/__init__.py
shore/util/ast.py
shore/util/changelog.py
shore/util/classifiers.py
shore/util/license.py
shore/util/resources.py
shore/util/text.py
shore/util/version.py
nr.shore-1.0.1.dist-info/LICENSE.txt
nr.shore-1.0.1.dist-info/METADATA
nr.shore-1.0.1.dist-info/WHEEL
nr.shore-1.0.1.dist-info/entry_points.txt
nr.shore-1.0.1.dist-info/top_level.txt
nr.shore-1.0.1.dist-info/RECORD
